openapi_mcp_generator/__init__.py
openapi_mcp_generator/cli.py
openapi_mcp_generator/generator.py
openapi_mcp_generator/generators.py
openapi_mcp_generator/http.py
openapi_mcp_generator/parser.py
openapi_mcp_generator/project.py
openapi_mcp_generator-0.1.1.dist-info/licenses/LICENSE
templates/__init__.py
templates/pyproject.toml
templates/requirements.txt
templates/config/.env.sh
templates/docker/Dockerfile
templates/docker/docker.sh
templates/server/mcp_server.py
openapi_mcp_generator-0.1.1.dist-info/METADATA
openapi_mcp_generator-0.1.1.dist-info/WHEEL
openapi_mcp_generator-0.1.1.dist-info/entry_points.txt
openapi_mcp_generator-0.1.1.dist-info/top_level.txt
openapi_mcp_generator-0.1.1.dist-info/RECORD
