Metadata-Version: 2.4
Name: openapi-mcp-generator
Version: 0.1.1
Summary: Generate MCP servers from OpenAPI specifications
License: MIT
Requires-Python: >=3.10
License-File: LICENSE
Requires-Dist: pyyaml>=6.0
Requires-Dist: jinja2>=3.1.2
Requires-Dist: httpx>=0.24.0
Requires-Dist: mcp[cli]>=0.1.0
Dynamic: license-file
